lmk/__init__.py
lmk/__main__.py
lmk/api_client.py
lmk/cli.py
lmk/cli_deps.py
lmk/constants.py
lmk/exc.py
lmk/instance.py
lmk/methods.py
lmk/patches.py
lmk/shell_cli.py
lmk/shell_cli.sh
lmk/generated/__init__.py
lmk/generated/api_client.py
lmk/generated/configuration.py
lmk/generated/exceptions.py
lmk/generated/rest.py
lmk/generated/api/__init__.py
lmk/generated/api/app_api.py
lmk/generated/api/event_api.py
lmk/generated/api/headless_auth_api.py
lmk/generated/api/notification_api.py
lmk/generated/api/oauth_api.py
lmk/generated/api/session_api.py
lmk/generated/models/__init__.py
lmk/generated/models/access_token_request.py
lmk/generated/models/access_token_response.py
lmk/generated/models/actor_response.py
lmk/generated/models/app_connection_self_response.py
lmk/generated/models/app_response.py
lmk/generated/models/create_headless_auth_session_request.py
lmk/generated/models/create_session_request.py
lmk/generated/models/create_session_request_state.py
lmk/generated/models/email_channel_payload.py
lmk/generated/models/event_notification_configuration.py
lmk/generated/models/event_request.py
lmk/generated/models/event_response.py
lmk/generated/models/headless_auth_refresh_token_request.py
lmk/generated/models/headless_auth_session_response.py
lmk/generated/models/jupyter_session_state.py
lmk/generated/models/none_session_state.py
lmk/generated/models/notification_channel_info.py
lmk/generated/models/notification_channel_response.py
lmk/generated/models/notification_channel_response_payload.py
lmk/generated/models/notification_channels_response.py
lmk/generated/models/partial_jupyter_session_state.py
lmk/generated/models/partial_none_session_state.py
lmk/generated/models/partial_process_session_state.py
lmk/generated/models/process_send_signal_request.py
lmk/generated/models/process_session_state.py
lmk/generated/models/session_action_request.py
lmk/generated/models/session_action_request_body.py
lmk/generated/models/session_response.py
lmkapp-1.2.0.dist-info/METADATA
lmkapp-1.2.0.dist-info/WHEEL
lmkapp-1.2.0.dist-info/entry_points.txt
lmkapp-1.2.0.dist-info/licenses/LICENSE.txt
lmkapp-1.2.0.dist-info/RECORD
