Metadata-Version: 2.1
Name: lmkapp
Version: 1.2.0
Summary: Stop watching your code run
Project-URL: Homepage, https://github.com/lmkapp/lmk
Author-email: Cam Feenstra <me@camfeenstra.com>
License: Copyright 2023 Cameron Feenstra
License-File: LICENSE.txt
Keywords: IPython,Jupyter,Widgets
Classifier: Framework :: Jupyter
Classifier: Intended Audience :: Developers
Classifier: Intended Audience :: Science/Research
Classifier: Programming Language :: Python
Classifier: Programming Language :: Python :: 3
Classifier: Programming Language :: Python :: 3.7
Classifier: Programming Language :: Python :: 3.8
Classifier: Programming Language :: Python :: 3.9
Classifier: Programming Language :: Python :: 3.10
Classifier: Programming Language :: Python :: 3.11
Requires-Python: >=3.7
Requires-Dist: aiohttp<4
Requires-Dist: blinker<2
Requires-Dist: pydantic<2
Requires-Dist: python-dateutil<3
Requires-Dist: typing-extensions<4.7
Requires-Dist: urllib3<2
Provides-Extra: cli
Requires-Dist: aiosqlite<1; extra == 'cli'
Requires-Dist: click<9; extra == 'cli'
Requires-Dist: psutil; extra == 'cli'
Requires-Dist: sqlalchemy[asyncio]<3,>=2; extra == 'cli'
Provides-Extra: dev
Requires-Dist: build>=1.0.0; extra == 'dev'
Requires-Dist: bump2version==1.*; extra == 'dev'
Requires-Dist: jupyterlab==4.*; extra == 'dev'
Requires-Dist: ruff==0.5.4; extra == 'dev'
Requires-Dist: tox>=4.2; extra == 'dev'
Provides-Extra: docs
Requires-Dist: novella~=0.2.6; extra == 'docs'
Requires-Dist: pydoc-markdown[novella]~=4.8.2; extra == 'docs'
Provides-Extra: jupyter
Requires-Dist: ipykernel; extra == 'jupyter'
Requires-Dist: ipython>=6.1.0; extra == 'jupyter'
Requires-Dist: ipywidgets>=7.0.0; extra == 'jupyter'
Provides-Extra: publish
Requires-Dist: twine; extra == 'publish'
Provides-Extra: test
Requires-Dist: jupyterlab; extra == 'test'
Requires-Dist: notebook; extra == 'test'
Requires-Dist: pytest-asyncio~=0.21.1; extra == 'test'
Requires-Dist: pytest~=7.4.0; extra == 'test'
Requires-Dist: selenium==4.16.0; extra == 'test'
Requires-Dist: webdriver-manager~=4.0.1; extra == 'test'
Provides-Extra: types
Requires-Dist: mypy<2,>=1; extra == 'types'
Requires-Dist: types-psutil; extra == 'types'
Requires-Dist: types-python-dateutil; extra == 'types'
